Garfield/.gitignore
Garfield/__init__.py
Garfield/_settings.py
Garfield/_version.py
Garfield/.idea/misc.xml
Garfield/.idea/modules.xml
Garfield/.idea/workspace.xml
Garfield/.idea/inspectionProfiles/profiles_settings.xml
Garfield/analysis/__init__.py
Garfield/analysis/calc_neighbor_prop.py
Garfield/analysis/calc_niches_enrich.py
Garfield/analysis/calc_niches_marker.py
Garfield/data/__init__.py
Garfield/data/dataloaders.py
Garfield/data/dataprocessors.py
Garfield/data/datareaders.py
Garfield/data/datasets.py
Garfield/data/gene_anno/hg19_genes.bed
Garfield/data/gene_anno/hg38_genes.bed
Garfield/data/gene_anno/mm10_genes.bed
Garfield/data/gene_anno/mm9_genes.bed
Garfield/data/gene_anno/protein_gene_conversion.csv
Garfield/model/Garfield.py
Garfield/model/__init__.py
Garfield/model/basemodelmixin.py
Garfield/model/utils.py
Garfield/modules/GNNModelVAE.py
Garfield/modules/__init__.py
Garfield/modules/loss.py
Garfield/modules/utils.py
Garfield/nn/__init__.py
Garfield/nn/decoders.py
Garfield/nn/encoders.py
Garfield/nn/utils.py
Garfield/plot/__init__.py
Garfield/plot/spatial_plot.py
Garfield/preprocessing/__init__.py
Garfield/preprocessing/_graph.py
Garfield/preprocessing/_utils.py
Garfield/preprocessing/adj_construction.py
Garfield/preprocessing/match_utils.py
Garfield/preprocessing/preprocess.py
Garfield/preprocessing/preprocess_utils.py
Garfield/trainer/__init__.py
Garfield/trainer/basetrainermixin.py
Garfield/trainer/metrics.py
Garfield/trainer/trainer.py
Garfield/trainer/utils.py
Garfield-1.0.0.dist-info/LICENSE
Garfield-1.0.0.dist-info/METADATA
Garfield-1.0.0.dist-info/WHEEL
Garfield-1.0.0.dist-info/top_level.txt
Garfield-1.0.0.dist-info/RECORD
