Metadata-Version: 2.1
Name: Garfield
Version: 1.0.0
Summary: Garfield: Graph-based Contrastive Learning enable Fast Single-Cell Embedding
Home-page: https://github.com/zhou-1314/Garfield
Author: Weige Zhou
Author-email: zhouwg1314@gmail.com
License: BSD
Classifier: Programming Language :: Python :: 3
Classifier: License :: OSI Approved :: BSD License
Classifier: Operating System :: OS Independent
Requires-Python: >=3.7
License-File: LICENSE
Requires-Dist: numpy >=1.17.0
Requires-Dist: pandas !=1.1,>=1.0
Requires-Dist: dill >=0.3.8
Requires-Dist: anndata !=0.10.9,>=0.7.4
Requires-Dist: scanpy >=1.9.6
Requires-Dist: muon >=0.1.6
Requires-Dist: scikit-learn >=0.19
Requires-Dist: scipy >=1.4
Requires-Dist: igraph >=0.10.8
Requires-Dist: leidenalg >=0.10.1
Requires-Dist: kneed >=0.7
Requires-Dist: seaborn >=0.11
Requires-Dist: matplotlib >=3.3
Requires-Dist: scikit-misc >=0.1.3
Requires-Dist: adjusttext >=0.7.3
Requires-Dist: umap-learn >=0.3.0
Requires-Dist: pybedtools >=0.8.0
Requires-Dist: torch-geometric >=2.4.0
Requires-Dist: tables
